edamame/__init__.py
edamame/generic.py
edamame/auth.py
edamame/utils.py
edamame/base.py
django_edamame-0.1.dist-info/top_level.txt
django_edamame-0.1.dist-info/WHEEL
django_edamame-0.1.dist-info/METADATA
django_edamame-0.1.dist-info/pydist.json
django_edamame-0.1.dist-info/RECORD
django_edamame-0.1.dist-info/DESCRIPTION.rst
