Metadata-Version: 2.0
Name: django-edamame
Version: 0.1
Summary: One idea of Class-based view module.
Home-page: https://github.com/tokibito/django-edamame
Author: Shinya Okano
Author-email: tokibito@gmail.com
License: UNKNOWN
Platform: UNKNOWN
Classifier: Development Status :: 3 - Alpha
Classifier: Framework :: Django
Classifier: Programming Language :: Python :: 2.7
Classifier: Programming Language :: Python :: 3
Classifier: License :: OSI Approved :: MIT License
Requires-Dist: Django
